MarkdownRumenCankao/README.md
MarkdownRumenCankao/__init__.py
MarkdownRumenCankao/__main__.py
MarkdownRumenCankao/file.epub
MarkdownRumenCankao/index.html
MarkdownRumenCankao/css/__init__.py
MarkdownRumenCankao/css/annotations.css
MarkdownRumenCankao/css/main.css
MarkdownRumenCankao/css/normalize.css
MarkdownRumenCankao/css/popup.css
MarkdownRumenCankao/font/__init__.py
MarkdownRumenCankao/font/fontello.eot
MarkdownRumenCankao/font/fontello.svg
MarkdownRumenCankao/font/fontello.ttf
MarkdownRumenCankao/font/fontello.woff
MarkdownRumenCankao/img/__init__.py
MarkdownRumenCankao/img/annotator-glyph-sprite.png
MarkdownRumenCankao/img/annotator-icon-sprite.png
MarkdownRumenCankao/img/apple-touch-icon.png
MarkdownRumenCankao/img/cancelfullscreen.png
MarkdownRumenCankao/img/close.png
MarkdownRumenCankao/img/fullscreen.png
MarkdownRumenCankao/img/loader.gif
MarkdownRumenCankao/img/menu-icon.png
MarkdownRumenCankao/img/save.png
MarkdownRumenCankao/img/saved.png
MarkdownRumenCankao/img/settings-s.png
MarkdownRumenCankao/img/settings.png
MarkdownRumenCankao/img/star.png
MarkdownRumenCankao/js/__init__.py
MarkdownRumenCankao/js/epub.js
MarkdownRumenCankao/js/epub.min.js
MarkdownRumenCankao/js/epub.min.map
MarkdownRumenCankao/js/hooks.min.js
MarkdownRumenCankao/js/hooks.min.map
MarkdownRumenCankao/js/reader.js
MarkdownRumenCankao/js/reader.js.map
MarkdownRumenCankao/js/reader.min.js
MarkdownRumenCankao/js/reader.min.map
MarkdownRumenCankao/js/hooks/__init__.py
MarkdownRumenCankao/js/hooks/extensions/__init__.py
MarkdownRumenCankao/js/hooks/extensions/highlight.js
MarkdownRumenCankao/js/libs/__init__.py
MarkdownRumenCankao/js/libs/jquery.min.js
MarkdownRumenCankao/js/libs/localforage.min.js
MarkdownRumenCankao/js/libs/screenfull.js
MarkdownRumenCankao/js/libs/screenfull.min.js
MarkdownRumenCankao/js/libs/zip.min.js
MarkdownRumenCankao/js/plugins/__init__.py
MarkdownRumenCankao/js/plugins/hypothesis.js
MarkdownRumenCankao/js/plugins/search.js
markdown_rumen_cankao-2024.3.4.0.dist-info/METADATA
markdown_rumen_cankao-2024.3.4.0.dist-info/WHEEL
markdown_rumen_cankao-2024.3.4.0.dist-info/entry_points.txt
markdown_rumen_cankao-2024.3.4.0.dist-info/top_level.txt
markdown_rumen_cankao-2024.3.4.0.dist-info/RECORD
